quickfix50sp1.py
_quickfix.cpython-310-x86_64-linux-gnu.so
quickfix42.py
quickfix50.py
quickfix.py
quickfix50sp2.py
quickfixt11.py
quickfix43.py
quickfix40.py
quickfix44.py
quickfix41.py
quickfix_binary-1.15.1.data/data/share/quickfix/FIX44.xml
quickfix_binary-1.15.1.data/data/share/quickfix/FIX42.xml
quickfix_binary-1.15.1.data/data/share/quickfix/FIX43.xml
quickfix_binary-1.15.1.data/data/share/quickfix/FIX40.xml
quickfix_binary-1.15.1.data/data/share/quickfix/FIX50.xml
quickfix_binary-1.15.1.data/data/share/quickfix/FIX50SP1.xml
quickfix_binary-1.15.1.data/data/share/quickfix/FIX41.xml
quickfix_binary-1.15.1.data/data/share/quickfix/FIXT11.xml
quickfix_binary-1.15.1.data/data/share/quickfix/FIX50SP2.xml
quickfix_binary-1.15.1.dist-info/LICENSE
quickfix_binary-1.15.1.dist-info/WHEEL
quickfix_binary-1.15.1.dist-info/RECORD
quickfix_binary-1.15.1.dist-info/METADATA
quickfix_binary-1.15.1.dist-info/top_level.txt
