Metadata-Version: 2.1
Name: quickfix-binary
Version: 1.15.1
Summary: FIX (Financial Information eXchange) protocol implementation
Home-page: http://www.quickfixengine.org
Author: Oren Miller
Author-email: oren@quickfixengine.org
Maintainer: Dennis Thanner
License: The QuickFIX Software License, Version 1.0         
Download-URL: http://www.quickfixengine.org
Platform: UNKNOWN
License-File: LICENSE
